python_rdrsegmenter/__init__.py
python_rdrsegmenter/rdrsegmenter.jar
python_rdrsegmenter/rdrsegmenter.py
python_rdrsegmenter/vi-vocab
python_rdrsegmenter/wordsegmenter.rdr
python_rdrsegmenter-0.1.1.dist-info/LICENSE.txt
python_rdrsegmenter-0.1.1.dist-info/METADATA
python_rdrsegmenter-0.1.1.dist-info/WHEEL
python_rdrsegmenter-0.1.1.dist-info/top_level.txt
python_rdrsegmenter-0.1.1.dist-info/RECORD
