Metadata-Version: 2.1
Name: python-rdrsegmenter
Version: 0.1.1
Summary: python_rdrsegmenter
Home-page: https://github.com/NgHoangDat/python_rdrsegmenter.git
Author: nghoangdat
Author-email: 18.hoang.dat.12@gmail.com
License: UNKNOWN
Download-URL: https://github.com/NgHoangDat/python_rdrsegmenter/archive/v0.1.1.tar.gz
Keywords: python-rdrsegmenter rdrsegmenter nlp vietnamese-nlp parser word-segmentation tokenizer
Platform: UNKNOWN
Classifier: Programming Language :: Python :: 3
Classifier: License :: OSI Approved :: MIT License
Classifier: Operating System :: OS Independent
Classifier: Topic :: Text Processing :: Linguistic
Requires-Python: >=3.6
Requires-Dist: pyjnius
